{"entities":{"P1820":{"pageid":21403363,"ns":120,"title":"Property:P1820","lastrevid":1094776293,"modified":"2020-01-09T23:13:05Z","type":"property","datatype":"string","id":"P1820","labels":{"en":{"language":"en","value":"Open Food Facts food additive ID"},"ru":{"language":"ru","value":"\u043f\u0438\u0449\u0435\u0432\u0430\u044f \u0434\u043e\u0431\u0430\u0432\u043a\u0430 Open Food Facts"},"nl":{"language":"nl","value":"Open Food Facts-identificatiecode voor levensmiddelenadditief"},"fr":{"language":"fr","value":"identifiant Open Food Facts d'un additif alimentaire"},"pl":{"language":"pl","value":"identyfikator dodatku do \u017cywno\u015bci w Open Food Facts"},"de":{"language":"de","value":"Eintrag bei Open Food Facts"},"mk":{"language":"mk","value":"\u0434\u043e\u0434\u0430\u0442\u043e\u043a \u0432\u043e Open Food Facts"},"da":{"language":"da","value":"Open Food Facts-tils\u00e6tningsstof"},"ar":{"language":"ar","value":"\u0645\u0639\u0631\u0641 \u0645\u0636\u0627\u0641 \u063a\u0630\u0627\u0626\u064a \u0641\u064a \u062d\u0642\u0627\u0626\u0642 \u0627\u0644\u0623\u063a\u0630\u064a\u0629 \u0627\u0644\u0645\u0641\u062a\u0648\u062d\u0629"},"uk":{"language":"uk","value":"\u0456\u0434\u0435\u043d\u0442\u0438\u0444\u0456\u043a\u0430\u0442\u043e\u0440 \u0445\u0430\u0440\u0447\u043e\u0432\u043e\u0457 \u0434\u043e\u0431\u0430\u0432\u043a\u0438 Open Food Facts"},"be-tarask":{"language":"be-tarask","value":"\u0456\u0434\u044d\u043d\u0442\u044b\u0444\u0456\u043a\u0430\u0442\u0430\u0440 \u0445\u0430\u0440\u0447\u043e\u0432\u0430\u0433\u0430 \u0434\u0430\u0434\u0430\u0442\u043a\u0443 Open Food Facts"},"nn":{"language":"nn","value":"Open Food Facts-id"},"ca":{"language":"ca","value":"identificador Open Food Facts food d'additiu alimentari"},"tt":{"language":"tt","value":"Open Food Facts \u0430\u0437\u044b\u043a \u04e9\u0441\u0442\u04d9\u043c\u04d9\u0441\u0435"},"nb":{"language":"nb","value":"Open Food Facts-ID"},"eo":{"language":"eo","value":"identigilo de man\u011da aldona\u0135o la\u016d Open Food Facts"},"it":{"language":"it","value":"identificativo Open Food Facts di un additivo"},"es":{"language":"es","value":"identificador de aditivo alimentario Open Food Facts"}},"descriptions":{"en":{"language":"en","value":"represents a food additive on Open Food Facts"},"nl":{"language":"nl","value":"staat voor een levensmiddelenadditief op Open Food Facts"},"fr":{"language":"fr","value":"repr\u00e9sente un additif alimentaire sur Open Food Facts"},"pl":{"language":"pl","value":"identyfikator dodatku do \u017cywno\u015bci w bazie Open Food Facts"},"uk":{"language":"uk","value":"\u043a\u043e\u0434 \u0445\u0430\u0440\u0447\u043e\u0432\u043e\u0457 \u0434\u043e\u0431\u0430\u0432\u043a\u0438 \u043d\u0430 Open Food Facts"},"be-tarask":{"language":"be-tarask","value":"\u0456\u0434\u044d\u043d\u0442\u044b\u0444\u0456\u043a\u0430\u0442\u0430\u0440 \u0445\u0430\u0440\u0447\u043e\u0432\u0430\u0433\u0430 \u0434\u0430\u0434\u0430\u0442\u043a\u0443 \u043d\u0430 Open Food Facts"},"nb":{"language":"nb","value":"identifikator for et tilsetningsstoff i databasen Open Food Facts"},"es":{"language":"es","value":"representa un aditivo alimentario en Open Food Facts"}},"aliases":{"ar":[{"language":"ar","value":"\u0645\u0636\u0627\u0641 \u063a\u0630\u0627\u0626\u064a \u0641\u064a \u062d\u0642\u0627\u0626\u0642 \u0627\u0644\u0623\u063a\u0630\u064a\u0629 \u0627\u0644\u0645\u0641\u062a\u0648\u062d\u0629"}],"nn":[{"language":"nn","value":"OFF-id"}],"nb":[{"language":"nb","value":"OFF-ID"}]},"claims":{"P31":[{"mainsnak":{"snaktype":"value","property":"P31","datavalue":{"value":{"entity-type":"item","numeric-id":23038310,"id":"Q23038310"},"type":"wikibase-entityid"},"datatype":"wikibase-item"},"type":"statement","id":"P1820$17624a9d-4c40-c125-6165-ef8af8c10654","rank":"normal"},{"mainsnak":{"snaktype":"value","property":"P31","datavalue":{"value":{"entity-type":"item","numeric-id":62589316,"id":"Q62589316"},"type":"wikibase-entityid"},"datatype":"wikibase-item"},"type":"statement","id":"P1820$aff901d2-4b5d-53c5-8fe6-c8f72f8f83a4","rank":"normal"}],"P1630":[{"mainsnak":{"snaktype":"value","property":"P1630","datavalue":{"value":"https://world.openfoodfacts.org/additive/$1","type":"string"},"datatype":"string"},"type":"statement","id":"P1820$f991c739-45c4-2af8-4c30-ae72da32cf57","rank":"normal"}],"P1793":[{"mainsnak":{"snaktype":"value","property":"P1793","datavalue":{"value":"[a-z0-9-]+","type":"string"},"datatype":"string"},"type":"statement","id":"P1820$e953bb3c-473d-0885-c544-4b69fc393493","rank":"normal"}],"P1855":[{"mainsnak":{"snaktype":"value","property":"P1855","datavalue":{"value":{"entity-type":"item","numeric-id":320617,"id":"Q320617"},"type":"wikibase-entityid"},"datatype":"wikibase-item"},"type":"statement","qualifiers":{"P1820":[{"snaktype":"value","property":"P1820","hash":"fb65f8a9a1f44579eb76ae1abb2b00e65874a940","datavalue":{"value":"e120-cochineal","type":"string"},"datatype":"string"}]},"qualifiers-order":["P1820"],"id":"P1820$D684D824-9C8D-49BC-A27F-7E663C3A413B","rank":"normal"}],"P1659":[{"mainsnak":{"snaktype":"value","property":"P1659","datavalue":{"value":{"entity-type":"property","numeric-id":1821,"id":"P1821"},"type":"wikibase-entityid"},"datatype":"wikibase-property"},"type":"statement","id":"P1820$97be62b8-4e9c-dbe0-4cc0-370e9405feb5","rank":"normal"},{"mainsnak":{"snaktype":"value","property":"P1659","datavalue":{"value":{"entity-type":"property","numeric-id":5930,"id":"P5930"},"type":"wikibase-entityid"},"datatype":"wikibase-property"},"type":"statement","id":"P1820$A93F1910-675A-4D17-ADDF-CBD1E7C58147","rank":"normal","references":[{"hash":"8fc46440ef0f288c776049a78db996125a9b7605","snaks":{"P4656":[{"snaktype":"value","property":"P4656","datavalue":{"value":"https://www.wikidata.org/w/index.php?title=Wikidata:Property_proposal/Open_Food_Facts_ingredient_ID&oldid=755673028","type":"string"},"datatype":"url"}]},"snaks-order":["P4656"]}]}],"P2264":[{"mainsnak":{"snaktype":"value","property":"P2264","datavalue":{"value":"200","type":"string"},"datatype":"external-id"},"type":"statement","id":"P1820$ECE881FE-B97C-432E-BF9B-51C9841E7D4F","rank":"normal"}],"P1896":[{"mainsnak":{"snaktype":"value","property":"P1896","datavalue":{"value":"https://world.openfoodfacts.org/additives","type":"string"},"datatype":"url"},"type":"statement","id":"P1820$5E50FD2D-AE53-49A9-9AAD-8FAD0E7F7BDB","rank":"normal"}],"P3254":[{"mainsnak":{"snaktype":"value","property":"P3254","datavalue":{"value":"https://www.wikidata.org/wiki/Wikidata:Property_proposal/Archive/30#P1820","type":"string"},"datatype":"url"},"type":"statement","id":"P1820$C16FBD80-0386-41F5-984C-90293F91D17E","rank":"normal"}],"P2302":[{"mainsnak":{"snaktype":"value","property":"P2302","datavalue":{"value":{"entity-type":"item","numeric-id":19474404,"id":"Q19474404"},"type":"wikibase-entityid"},"datatype":"wikibase-item"},"type":"statement","id":"P1820$9FCFEFE4-2DF8-4D0F-8CD9-72AB0FEE9ECC","rank":"normal"},{"mainsnak":{"snaktype":"value","property":"P2302","datavalue":{"value":{"entity-type":"item","numeric-id":21502410,"id":"Q21502410"},"type":"wikibase-entityid"},"datatype":"wikibase-item"},"type":"statement","id":"P1820$0E5F4532-3846-40BF-BEB2-B6CE546F56A6","rank":"normal"},{"mainsnak":{"snaktype":"value","property":"P2302","datavalue":{"value":{"entity-type":"item","numeric-id":21503250,"id":"Q21503250"},"type":"wikibase-entityid"},"datatype":"wikibase-item"},"type":"statement","qualifiers":{"P2309":[{"snaktype":"value","property":"P2309","hash":"8fb539b5b9fd607316a1edaf9f8fd42a67a51dd2","datavalue":{"value":{"entity-type":"item","numeric-id":30208840,"id":"Q30208840"},"type":"wikibase-entityid"},"datatype":"wikibase-item"}],"P2308":[{"snaktype":"value","property":"P2308","hash":"dc01045821b12aebd1666c7a0b37dfa0ef968466","datavalue":{"value":{"entity-type":"item","numeric-id":189567,"id":"Q189567"},"type":"wikibase-entityid"},"datatype":"wikibase-item"}]},"qualifiers-order":["P2309","P2308"],"id":"P1820$E4BB093E-DAD3-4C86-A7C6-3092F53DED0B","rank":"normal"},{"mainsnak":{"snaktype":"value","property":"P2302","datavalue":{"value":{"entity-type":"item","numeric-id":21503247,"id":"Q21503247"},"type":"wikibase-entityid"},"datatype":"wikibase-item"},"type":"statement","qualifiers":{"P2306":[{"snaktype":"value","property":"P2306","hash":"6b1b6155d2d25b73d6a39fe60d6d98d935353199","datavalue":{"value":{"entity-type":"property","numeric-id":628,"id":"P628"},"type":"wikibase-entityid"},"datatype":"wikibase-property"}]},"qualifiers-order":["P2306"],"id":"P1820$EBF8CD6F-73C6-421A-B6AD-2B2BA782D04B","rank":"normal"},{"mainsnak":{"snaktype":"value","property":"P2302","datavalue":{"value":{"entity-type":"item","numeric-id":21502404,"id":"Q21502404"},"type":"wikibase-entityid"},"datatype":"wikibase-item"},"type":"statement","qualifiers":{"P1793":[{"snaktype":"value","property":"P1793","hash":"c7be905a4a26065f9edf97993317a66210ccc69d","datavalue":{"value":"[a-z0-9-]+","type":"string"},"datatype":"string"}]},"qualifiers-order":["P1793"],"id":"P1820$D066AFB5-35CC-4C0E-9EC8-EC4093F2DCB9","rank":"normal"}],"P3303":[{"mainsnak":{"snaktype":"value","property":"P3303","datavalue":{"value":"https://world.openbeautyfacts.org/additive/$1","type":"string"},"datatype":"string"},"type":"statement","id":"P1820$cf730ace-4756-e624-0828-ead177691004","rank":"normal"},{"mainsnak":{"snaktype":"value","property":"P3303","datavalue":{"value":"https://world.openpetfoodfacts.org/additive/$1","type":"string"},"datatype":"string"},"type":"statement","id":"P1820$70a490c1-49d9-108f-fb97-773156bd5ec8","rank":"normal"}],"P1629":[{"mainsnak":{"snaktype":"value","property":"P1629","datavalue":{"value":{"entity-type":"item","numeric-id":3353146,"id":"Q3353146"},"type":"wikibase-entityid"},"datatype":"wikibase-item"},"type":"statement","id":"P1820$a00c5fc6-4f10-98c4-125c-c87cdf19f8af","rank":"normal"}]}}}}