{"entities":{"P4740":{"pageid":48258906,"ns":120,"title":"Property:P4740","lastrevid":1056269555,"modified":"2019-11-19T11:52:51Z","type":"property","datatype":"external-id","id":"P4740","labels":{"en":{"language":"en","value":"Brooklyn Museum artwork ID"},"fr":{"language":"fr","value":"identifiant Brooklyn Museum d'une \u0153uvre d'art"},"uk":{"language":"uk","value":"\u0456\u0434\u0435\u043d\u0442\u0438\u0444\u0456\u043a\u0430\u0442\u043e\u0440 \u0442\u0432\u043e\u0440\u0443 Brooklyn Museum"},"ar":{"language":"ar","value":"\u0645\u0639\u0631\u0641 \u0639\u0645\u0644 \u0641\u0646\u064a \u0641\u064a \u0645\u062a\u062d\u0641 \u0628\u0631\u0648\u0643\u0644\u064a\u0646"},"pl":{"language":"pl","value":"identyfikator Brooklyn Museum artwork ID"},"zh-hans":{"language":"zh-hans","value":"\u5e03\u9c81\u514b\u6797\u535a\u7269\u9986\u827a\u672f\u54c1\u7f16\u53f7"},"es":{"language":"es","value":"identificador Museo Brooklyn de obra de arte"},"nl":{"language":"nl","value":"Brooklyn Museum-identificatiecode voor kunstwerk"},"de":{"language":"de","value":"Kunstwerk ID des Brooklyn Museum"},"mk":{"language":"mk","value":"\u0434\u0435\u043b\u043e \u0432\u043e \u0411\u0440\u0443\u043a\u043b\u0438\u043d\u0441\u043a\u0438\u043e\u0442 \u043c\u0443\u0437\u0435\u0458"}},"descriptions":{"en":{"language":"en","value":"identifier for an artwork or other object on the Brooklyn Museum website"},"fr":{"language":"fr","value":"identifiant d'une \u0153uvre d'art ou d'un objet sur le site web du Brooklyn Museum"},"uk":{"language":"uk","value":"\u0456\u0434\u0435\u043d\u0442\u0438\u0444\u0456\u043a\u0430\u0442\u043e\u0440 \u0434\u043b\u044f \u043c\u0438\u0441\u0442\u0435\u0446\u044c\u043a\u043e\u0433\u043e \u0442\u0432\u043e\u0440\u0443 \u0430\u0431\u043e \u0456\u043d\u0448\u043e\u0433\u043e \u043e\u0431'\u0454\u043a\u0442\u0430 \u043d\u0430 \u0432\u0435\u0431-\u0441\u0430\u0439\u0442\u0456 Brooklyn Museum"},"zh-hans":{"language":"zh-hans","value":"\u5e03\u9c81\u514b\u6797\u535a\u7269\u9986\u7f51\u7ad9\u4e0a\u7684\u827a\u672f\u4f5c\u54c1\u6216\u5176\u4ed6\u7269\u54c1\u7684\u6807\u8bc6\u7b26"},"es":{"language":"es","value":"identificador de una obra de arte en el sitio web del Museo Brooklyn"},"de":{"language":"de","value":"Identifikator eines Kunstwerkes der Webseite des Brooklyn Museum"}},"aliases":{"ar":[{"language":"ar","value":"\u0639\u0645\u0644 \u0641\u0646\u064a \u0641\u064a \u0645\u062a\u062d\u0641 \u0628\u0631\u0648\u0643\u0644\u064a\u0646"}],"es":[{"language":"es","value":"Museo Brooklyn (obra de arte)"},{"language":"es","value":"Brooklyn Museum (obra de arte)"}]},"claims":{"P31":[{"mainsnak":{"snaktype":"value","property":"P31","datavalue":{"value":{"entity-type":"item","numeric-id":44847669,"id":"Q44847669"},"type":"wikibase-entityid"},"datatype":"wikibase-item"},"type":"statement","id":"P4740$7800b396-4cb9-5e78-1555-797f9400c9f3","rank":"normal"}],"P1629":[{"mainsnak":{"snaktype":"value","property":"P1629","datavalue":{"value":{"entity-type":"item","numeric-id":632682,"id":"Q632682"},"type":"wikibase-entityid"},"datatype":"wikibase-item"},"type":"statement","id":"P4740$323c3693-4275-64f4-c3cf-f0982d2fb909","rank":"normal"}],"P1793":[{"mainsnak":{"snaktype":"value","property":"P1793","datavalue":{"value":"[1-9]\\d*","type":"string"},"datatype":"string"},"type":"statement","id":"P4740$45c95119-490e-d51e-dce7-dc24269cd4d0","rank":"normal"}],"P1896":[{"mainsnak":{"snaktype":"value","property":"P1896","datavalue":{"value":"https://www.brooklynmuseum.org/opencollection/search/advanced","type":"string"},"datatype":"url"},"type":"statement","id":"P4740$ff1074b4-403c-706d-97c6-8c0da2091cb1","rank":"normal"}],"P1630":[{"mainsnak":{"snaktype":"value","property":"P1630","datavalue":{"value":"https://www.brooklynmuseum.org/opencollection/objects/$1","type":"string"},"datatype":"string"},"type":"statement","qualifiers":{"P407":[{"snaktype":"value","property":"P407","hash":"daf1c4fcb58181b02dff9cc89deb084004ddae4b","datavalue":{"value":{"entity-type":"item","numeric-id":1860,"id":"Q1860"},"type":"wikibase-entityid"},"datatype":"wikibase-item"}]},"qualifiers-order":["P407"],"id":"P4740$4e56fb28-4053-0e9a-403d-a9712137ee94","rank":"normal"}],"P1659":[{"mainsnak":{"snaktype":"value","property":"P1659","datavalue":{"value":{"entity-type":"property","numeric-id":2014,"id":"P2014"},"type":"wikibase-entityid"},"datatype":"wikibase-property"},"type":"statement","id":"P4740$f9c81fde-42cd-5cc3-98d3-e3a54b09d90e","rank":"normal"},{"mainsnak":{"snaktype":"value","property":"P1659","datavalue":{"value":{"entity-type":"property","numeric-id":3634,"id":"P3634"},"type":"wikibase-entityid"},"datatype":"wikibase-property"},"type":"statement","id":"P4740$a03bc259-4a2b-53a7-a42d-c3786caec3ca","rank":"normal"},{"mainsnak":{"snaktype":"value","property":"P1659","datavalue":{"value":{"entity-type":"property","numeric-id":4737,"id":"P4737"},"type":"wikibase-entityid"},"datatype":"wikibase-property"},"type":"statement","id":"P4740$703cc7db-4bf5-90f1-c83a-d99643b4fcb6","rank":"normal"},{"mainsnak":{"snaktype":"value","property":"P1659","datavalue":{"value":{"entity-type":"property","numeric-id":4899,"id":"P4899"},"type":"wikibase-entityid"},"datatype":"wikibase-property"},"type":"statement","id":"P4740$d9018f09-4101-88a1-f3dd-b5657815c531","rank":"normal"}],"P1855":[{"mainsnak":{"snaktype":"value","property":"P1855","datavalue":{"value":{"entity-type":"item","numeric-id":19858424,"id":"Q19858424"},"type":"wikibase-entityid"},"datatype":"wikibase-item"},"type":"statement","qualifiers":{"P4740":[{"snaktype":"value","property":"P4740","hash":"65abd09f3c7e060c95a4901da8d41b425794b1a2","datavalue":{"value":"4646","type":"string"},"datatype":"external-id"}]},"qualifiers-order":["P4740"],"id":"P4740$e1495434-4f4e-c15d-a19b-9ccd11f423ea","rank":"normal"},{"mainsnak":{"snaktype":"value","property":"P1855","datavalue":{"value":{"entity-type":"item","numeric-id":18178207,"id":"Q18178207"},"type":"wikibase-entityid"},"datatype":"wikibase-item"},"type":"statement","qualifiers":{"P4740":[{"snaktype":"value","property":"P4740","hash":"dc33f1937cd4663ce9a47c104f264e8a9da0f32d","datavalue":{"value":"4739","type":"string"},"datatype":"external-id"}]},"qualifiers-order":["P4740"],"id":"P4740$3f6090a1-462a-f4b3-c622-0509fa891bdf","rank":"normal"}],"P3254":[{"mainsnak":{"snaktype":"value","property":"P3254","datavalue":{"value":"https://www.wikidata.org/wiki/Wikidata:Property_proposal/Brooklyn_Museum_ID","type":"string"},"datatype":"url"},"type":"statement","id":"P4740$5adec348-458f-4e26-4a40-e5545210f643","rank":"normal"}],"P2302":[{"mainsnak":{"snaktype":"value","property":"P2302","datavalue":{"value":{"entity-type":"item","numeric-id":21502404,"id":"Q21502404"},"type":"wikibase-entityid"},"datatype":"wikibase-item"},"type":"statement","qualifiers":{"P1793":[{"snaktype":"value","property":"P1793","hash":"b11a207353fbbc014d3317bccfda3b8dba3ab975","datavalue":{"value":"[1-9]\\d*","type":"string"},"datatype":"string"}]},"qualifiers-order":["P1793"],"id":"P4740$7d1537dd-4ffb-69bc-bcbb-105e320dff4c","rank":"normal"},{"mainsnak":{"snaktype":"value","property":"P2302","datavalue":{"value":{"entity-type":"item","numeric-id":19474404,"id":"Q19474404"},"type":"wikibase-entityid"},"datatype":"wikibase-item"},"type":"statement","id":"P4740$feaba221-40f9-4ba0-e263-f422500de2c4","rank":"normal"},{"mainsnak":{"snaktype":"value","property":"P2302","datavalue":{"value":{"entity-type":"item","numeric-id":21502410,"id":"Q21502410"},"type":"wikibase-entityid"},"datatype":"wikibase-item"},"type":"statement","qualifiers":{"P2316":[{"snaktype":"value","property":"P2316","hash":"d50c571a43e6102d65b729ccc7049a0a2f867e34","datavalue":{"value":{"entity-type":"item","numeric-id":21502408,"id":"Q21502408"},"type":"wikibase-entityid"},"datatype":"wikibase-item"}]},"qualifiers-order":["P2316"],"id":"P4740$296074d3-4910-532d-e563-ef66f76a39d9","rank":"normal"},{"mainsnak":{"snaktype":"value","property":"P2302","datavalue":{"value":{"entity-type":"item","numeric-id":21503250,"id":"Q21503250"},"type":"wikibase-entityid"},"datatype":"wikibase-item"},"type":"statement","qualifiers":{"P2308":[{"snaktype":"value","property":"P2308","hash":"ff4d9cc9c8e7e696fa908009fdb888b30e3a5312","datavalue":{"value":{"entity-type":"item","numeric-id":838948,"id":"Q838948"},"type":"wikibase-entityid"},"datatype":"wikibase-item"}],"P2309":[{"snaktype":"value","property":"P2309","hash":"8d7afee22e0fa6211dd8c95f247e1dd7b38daf70","datavalue":{"value":{"entity-type":"item","numeric-id":21503252,"id":"Q21503252"},"type":"wikibase-entityid"},"datatype":"wikibase-item"}]},"qualifiers-order":["P2308","P2309"],"id":"P4740$c4619077-4d42-9f2d-cfda-6a309e5262d2","rank":"normal"},{"mainsnak":{"snaktype":"value","property":"P2302","datavalue":{"value":{"entity-type":"item","numeric-id":21503247,"id":"Q21503247"},"type":"wikibase-entityid"},"datatype":"wikibase-item"},"type":"statement","qualifiers":{"P2306":[{"snaktype":"value","property":"P2306","hash":"0182d11f88bb66d4d44e15f5e49162f13425c6e0","datavalue":{"value":{"entity-type":"property","numeric-id":195,"id":"P195"},"type":"wikibase-entityid"},"datatype":"wikibase-property"}],"P2305":[{"snaktype":"value","property":"P2305","hash":"8e5141953d36f66a526113f5b908af996f1613e1","datavalue":{"value":{"entity-type":"item","numeric-id":632682,"id":"Q632682"},"type":"wikibase-entityid"},"datatype":"wikibase-item"}]},"qualifiers-order":["P2306","P2305"],"id":"P4740$ad38d045-469b-12b7-f8bb-19de6f6fc1f9","rank":"normal"},{"mainsnak":{"snaktype":"value","property":"P2302","datavalue":{"value":{"entity-type":"item","numeric-id":21503247,"id":"Q21503247"},"type":"wikibase-entityid"},"datatype":"wikibase-item"},"type":"statement","qualifiers":{"P2306":[{"snaktype":"value","property":"P2306","hash":"0a59732a9b016f05aed6fa85fdd0c42bd40bb3c4","datavalue":{"value":{"entity-type":"property","numeric-id":170,"id":"P170"},"type":"wikibase-entityid"},"datatype":"wikibase-property"}]},"qualifiers-order":["P2306"],"id":"P4740$d092b852-4238-f9ab-87de-6a26b710162f","rank":"normal"},{"mainsnak":{"snaktype":"value","property":"P2302","datavalue":{"value":{"entity-type":"item","numeric-id":21503247,"id":"Q21503247"},"type":"wikibase-entityid"},"datatype":"wikibase-item"},"type":"statement","qualifiers":{"P2306":[{"snaktype":"value","property":"P2306","hash":"96257234359d122c390595f1a6571550720ed939","datavalue":{"value":{"entity-type":"property","numeric-id":571,"id":"P571"},"type":"wikibase-entityid"},"datatype":"wikibase-property"}]},"qualifiers-order":["P2306"],"id":"P4740$451a7024-4a2d-06b2-cdab-c58d93478a86","rank":"normal"},{"mainsnak":{"snaktype":"value","property":"P2302","datavalue":{"value":{"entity-type":"item","numeric-id":21503247,"id":"Q21503247"},"type":"wikibase-entityid"},"datatype":"wikibase-item"},"type":"statement","qualifiers":{"P2306":[{"snaktype":"value","property":"P2306","hash":"e259a3004577debad708308e552268c90ea40f04","datavalue":{"value":{"entity-type":"property","numeric-id":276,"id":"P276"},"type":"wikibase-entityid"},"datatype":"wikibase-property"}]},"qualifiers-order":["P2306"],"id":"P4740$86c0b9c3-4a25-92e6-9b04-01c44095e6bb","rank":"normal"},{"mainsnak":{"snaktype":"value","property":"P2302","datavalue":{"value":{"entity-type":"item","numeric-id":21503247,"id":"Q21503247"},"type":"wikibase-entityid"},"datatype":"wikibase-item"},"type":"statement","qualifiers":{"P2306":[{"snaktype":"value","property":"P2306","hash":"466102e7ff914fc728365d87bc24ff6ccf2dfde8","datavalue":{"value":{"entity-type":"property","numeric-id":217,"id":"P217"},"type":"wikibase-entityid"},"datatype":"wikibase-property"}]},"qualifiers-order":["P2306"],"id":"P4740$578d940a-462d-05ac-6ba8-40bd26886a21","rank":"normal"}],"P17":[{"mainsnak":{"snaktype":"value","property":"P17","datavalue":{"value":{"entity-type":"item","numeric-id":30,"id":"Q30"},"type":"wikibase-entityid"},"datatype":"wikibase-item"},"type":"statement","id":"P4740$163364e8-4996-86df-5133-b4f64e333dc6","rank":"normal"}],"P2875":[{"mainsnak":{"snaktype":"value","property":"P2875","datavalue":{"value":{"entity-type":"item","numeric-id":47216073,"id":"Q47216073"},"type":"wikibase-entityid"},"datatype":"wikibase-item"},"type":"statement","id":"P4740$cd54d357-4a49-d6fa-3212-accf13269cff","rank":"normal"}],"P2264":[{"mainsnak":{"snaktype":"value","property":"P2264","datavalue":{"value":"880","type":"string"},"datatype":"external-id"},"type":"statement","id":"P4740$5cf26524-4149-2fd4-29aa-025a131b3e0e","rank":"normal"}]}}}}