{"entities":{"P5259":{"pageid":54943752,"ns":120,"title":"Property:P5259","lastrevid":1045765687,"modified":"2019-11-05T16:31:15Z","type":"property","datatype":"external-id","id":"P5259","labels":{"en":{"language":"en","value":"Swedish Gravestone ID"},"fr":{"language":"fr","value":"identifiant Gravstensinventeringen"},"sv":{"language":"sv","value":"Gravstensinventeringen"},"uk":{"language":"uk","value":"\u0456\u0434\u0435\u043d\u0442\u0438\u0444\u0456\u043a\u0430\u0442\u043e\u0440 \u0448\u0432\u0435\u0434\u0441\u044c\u043a\u043e\u0433\u043e \u043d\u0430\u0434\u0433\u0440\u043e\u0431\u043a\u0430"},"ar":{"language":"ar","value":"\u0645\u0639\u0631\u0641 \u0634\u0627\u0647\u062f \u0642\u0628\u0631 \u0633\u0648\u064a\u062f\u064a"},"zh-hans":{"language":"zh-hans","value":"\u745e\u5178\u5893\u7891\u7f16\u53f7"},"nl":{"language":"nl","value":"Zweedse grafsteen-identificatiecode"}},"descriptions":{"en":{"language":"en","value":"register of +348 000 Swedish gravestones for +759,000 Swedish people"},"sv":{"language":"sv","value":"register med +348 000 svenska gravestenar"},"uk":{"language":"uk","value":"\u0440\u0435\u0454\u0441\u0442\u0440 +348 000 \u0448\u0432\u0435\u0434\u0441\u044c\u043a\u0438\u0445 \u043d\u0430\u0434\u0433\u0440\u043e\u0431\u043a\u0456\u0432 \u0434\u043b\u044f +759 000 \u0448\u0432\u0435\u0434\u0441\u044c\u043a\u0438\u0445 \u043b\u044e\u0434\u0435\u0439"}},"aliases":{"ar":[{"language":"ar","value":"\u0634\u0627\u0647\u062f \u0642\u0628\u0631 \u0633\u0648\u064a\u062f\u064a"}]},"claims":{"P31":[{"mainsnak":{"snaktype":"value","property":"P31","datavalue":{"value":{"entity-type":"item","numeric-id":19595382,"id":"Q19595382"},"type":"wikibase-entityid"},"datatype":"wikibase-item"},"type":"statement","id":"P5259$AA9C73AA-7BCC-4BCA-AC7A-5D2A11DF2062","rank":"normal"},{"mainsnak":{"snaktype":"value","property":"P31","datavalue":{"value":{"entity-type":"item","numeric-id":45484922,"id":"Q45484922"},"type":"wikibase-entityid"},"datatype":"wikibase-item"},"type":"statement","id":"P5259$caa457c3-49e3-3974-0597-875463283119","rank":"normal"},{"mainsnak":{"snaktype":"value","property":"P31","datavalue":{"value":{"entity-type":"item","numeric-id":56249073,"id":"Q56249073"},"type":"wikibase-entityid"},"datatype":"wikibase-item"},"type":"statement","id":"P5259$4554cd5d-4fa5-f934-5c2a-503203a9a807","rank":"normal"},{"mainsnak":{"snaktype":"value","property":"P31","datavalue":{"value":{"entity-type":"item","numeric-id":51122237,"id":"Q51122237"},"type":"wikibase-entityid"},"datatype":"wikibase-item"},"type":"statement","id":"P5259$77acb481-4ad6-ed4d-c795-be9b4a605c5e","rank":"normal"}],"P1629":[{"mainsnak":{"snaktype":"value","property":"P1629","datavalue":{"value":{"entity-type":"item","numeric-id":28736343,"id":"Q28736343"},"type":"wikibase-entityid"},"datatype":"wikibase-item"},"type":"statement","id":"P5259$CAB2B08F-5167-491B-97F4-0C9A3FC71A1A","rank":"normal","references":[{"hash":"57fb52f873535f123f530027d9a24a2fd97a5e94","snaks":{"P4656":[{"snaktype":"value","property":"P4656","datavalue":{"value":"https://www.wikidata.org/w/index.php?title=Wikidata:Property_proposal/Swedish_Gravestone_ID&oldid=691771362","type":"string"},"datatype":"url"}]},"snaks-order":["P4656"]}]}],"P3254":[{"mainsnak":{"snaktype":"value","property":"P3254","datavalue":{"value":"https://www.wikidata.org/wiki/Wikidata:Property_proposal/Swedish_Gravestone_ID","type":"string"},"datatype":"url"},"type":"statement","id":"P5259$C5C8DCF0-9A69-4671-95EB-5AB60AAEA631","rank":"normal"}],"P1630":[{"mainsnak":{"snaktype":"value","property":"P1630","datavalue":{"value":"http://grav.genealogi.se/Gravsokview.php?g_id=$1","type":"string"},"datatype":"string"},"type":"statement","id":"P5259$19C722D8-5892-4C16-8853-7BA99E5B7907","rank":"normal","references":[{"hash":"57fb52f873535f123f530027d9a24a2fd97a5e94","snaks":{"P4656":[{"snaktype":"value","property":"P4656","datavalue":{"value":"https://www.wikidata.org/w/index.php?title=Wikidata:Property_proposal/Swedish_Gravestone_ID&oldid=691771362","type":"string"},"datatype":"url"}]},"snaks-order":["P4656"]}]}],"P2302":[{"mainsnak":{"snaktype":"value","property":"P2302","datavalue":{"value":{"entity-type":"item","numeric-id":21502410,"id":"Q21502410"},"type":"wikibase-entityid"},"datatype":"wikibase-item"},"type":"statement","id":"P5259$C258C8FF-2C0A-407B-805A-9C03F13BB41E","rank":"normal","references":[{"hash":"57fb52f873535f123f530027d9a24a2fd97a5e94","snaks":{"P4656":[{"snaktype":"value","property":"P4656","datavalue":{"value":"https://www.wikidata.org/w/index.php?title=Wikidata:Property_proposal/Swedish_Gravestone_ID&oldid=691771362","type":"string"},"datatype":"url"}]},"snaks-order":["P4656"]}]},{"mainsnak":{"snaktype":"value","property":"P2302","datavalue":{"value":{"entity-type":"item","numeric-id":21502404,"id":"Q21502404"},"type":"wikibase-entityid"},"datatype":"wikibase-item"},"type":"statement","qualifiers":{"P1793":[{"snaktype":"value","property":"P1793","hash":"b11a207353fbbc014d3317bccfda3b8dba3ab975","datavalue":{"value":"[1-9]\\d*","type":"string"},"datatype":"string"}]},"qualifiers-order":["P1793"],"id":"P5259$D32988B8-2292-4491-9ED3-23193EEE881B","rank":"normal","references":[{"hash":"57fb52f873535f123f530027d9a24a2fd97a5e94","snaks":{"P4656":[{"snaktype":"value","property":"P4656","datavalue":{"value":"https://www.wikidata.org/w/index.php?title=Wikidata:Property_proposal/Swedish_Gravestone_ID&oldid=691771362","type":"string"},"datatype":"url"}]},"snaks-order":["P4656"]}]}],"P1793":[{"mainsnak":{"snaktype":"value","property":"P1793","datavalue":{"value":"[1-9]\\d*","type":"string"},"datatype":"string"},"type":"statement","id":"P5259$E635CB55-E46D-4CB7-BF1A-E0E45C134DFF","rank":"normal","references":[{"hash":"57fb52f873535f123f530027d9a24a2fd97a5e94","snaks":{"P4656":[{"snaktype":"value","property":"P4656","datavalue":{"value":"https://www.wikidata.org/w/index.php?title=Wikidata:Property_proposal/Swedish_Gravestone_ID&oldid=691771362","type":"string"},"datatype":"url"}]},"snaks-order":["P4656"]}]}],"P1855":[{"mainsnak":{"snaktype":"value","property":"P1855","datavalue":{"value":{"entity-type":"item","numeric-id":43247,"id":"Q43247"},"type":"wikibase-entityid"},"datatype":"wikibase-item"},"type":"statement","qualifiers":{"P5259":[{"snaktype":"value","property":"P5259","hash":"376c911982acee91abedba22ada3b85877b16a79","datavalue":{"value":"281603","type":"string"},"datatype":"external-id"}]},"qualifiers-order":["P5259"],"id":"P5259$3EA4761F-EF51-44DB-B33B-84E02299AC4C","rank":"normal","references":[{"hash":"57fb52f873535f123f530027d9a24a2fd97a5e94","snaks":{"P4656":[{"snaktype":"value","property":"P4656","datavalue":{"value":"https://www.wikidata.org/w/index.php?title=Wikidata:Property_proposal/Swedish_Gravestone_ID&oldid=691771362","type":"string"},"datatype":"url"}]},"snaks-order":["P4656"]}]}],"P4876":[{"mainsnak":{"snaktype":"value","property":"P4876","datavalue":{"value":{"amount":"+348000","unit":"1"},"type":"quantity"},"datatype":"quantity"},"type":"statement","qualifiers":{"P585":[{"snaktype":"value","property":"P585","hash":"e7d6c72dc86467549b68f287124aed4a196afeb0","datavalue":{"value":{"time":"+2018-06-00T00:00:00Z","timezone":0,"before":0,"after":0,"precision":10,"calendarmodel":"http://www.wikidata.org/entity/Q1985727"},"type":"time"},"datatype":"time"}]},"qualifiers-order":["P585"],"id":"P5259$FA4A1774-70CB-42E3-9AC3-3FFAF5D097F6","rank":"normal","references":[{"hash":"57fb52f873535f123f530027d9a24a2fd97a5e94","snaks":{"P4656":[{"snaktype":"value","property":"P4656","datavalue":{"value":"https://www.wikidata.org/w/index.php?title=Wikidata:Property_proposal/Swedish_Gravestone_ID&oldid=691771362","type":"string"},"datatype":"url"}]},"snaks-order":["P4656"]}]}],"P17":[{"mainsnak":{"snaktype":"value","property":"P17","datavalue":{"value":{"entity-type":"item","numeric-id":34,"id":"Q34"},"type":"wikibase-entityid"},"datatype":"wikibase-item"},"type":"statement","id":"P5259$24b26fb7-4019-df9a-3b23-61df6201857b","rank":"normal"}]}}}}