{"entities":{"P5733":{"pageid":56270652,"ns":120,"title":"Property:P5733","lastrevid":970254073,"modified":"2019-06-28T03:12:20Z","type":"property","datatype":"external-id","id":"P5733","labels":{"en":{"language":"en","value":"bilibili ID"},"zh":{"language":"zh","value":"\u55f6\u54e9\u55f6\u54e9\u4f5c\u54c1\u6a19\u8b58\u7b26"},"fr":{"language":"fr","value":"identifiant Bilibili"},"ar":{"language":"ar","value":"\u0645\u0639\u0631\u0641 \u0628\u064a\u0644\u064a\u0628\u064a\u0644\u064a"},"uk":{"language":"uk","value":"\u0456\u0434\u0435\u043d\u0442\u0438\u0444\u0456\u043a\u0430\u0442\u043e\u0440 bilibili"},"ca":{"language":"ca","value":"identificador bilibili"},"id":{"language":"id","value":"ID bilibili"},"nl":{"language":"nl","value":"Bilibili-identificatiecode"},"it":{"language":"it","value":"identificativo bilibili"}},"descriptions":{"en":{"language":"en","value":"identifier for an anime or drama topic on bilibili"},"uk":{"language":"uk","value":"\u0456\u0434\u0435\u043d\u0442\u0438\u0444\u0456\u043a\u0430\u0442\u043e\u0440 \u0434\u043b\u044f \u0442\u0435\u043c\u0438 \u0430\u043d\u0456\u043c\u0435 \u0430\u0431\u043e \u0434\u0440\u0430\u043c\u0438 \u043d\u0430 bilibili"},"zh":{"language":"zh","value":"\u55f6\u54e9\u55f6\u54e9\u4e0a\u52d5\u756b\u6216\u6232\u5287\u4e3b\u984c\u7684\u6a19\u8b58\u7b26"},"it":{"language":"it","value":"identificativo di un anime o di un drama su bilibili"},"id":{"language":"id","value":"penanda untuk topik anime atau drama di bilibili"}},"aliases":{"id":[{"language":"id","value":"penanda bilibili"}]},"claims":{"P3254":[{"mainsnak":{"snaktype":"value","property":"P3254","datavalue":{"value":"https://www.wikidata.org/wiki/Wikidata:Property_proposal/bilibili_ID","type":"string"},"datatype":"url"},"type":"statement","id":"P5733$D6E168BC-BAD0-4BF5-8ED4-A633DBE246AE","rank":"normal","references":[{"hash":"e58b97f86e2a3a4152287e2566013b4d99133e11","snaks":{"P4656":[{"snaktype":"value","property":"P4656","datavalue":{"value":"https://www.wikidata.org/w/index.php?title=Wikidata:Property_proposal/bilibili_ID&oldid=736360211","type":"string"},"datatype":"url"}]},"snaks-order":["P4656"]}]}],"P1629":[{"mainsnak":{"snaktype":"value","property":"P1629","datavalue":{"value":{"entity-type":"item","numeric-id":3077586,"id":"Q3077586"},"type":"wikibase-entityid"},"datatype":"wikibase-item"},"type":"statement","id":"P5733$6B29BF2F-E4A6-4D10-ABAE-61D41C05F2A9","rank":"normal","references":[{"hash":"e58b97f86e2a3a4152287e2566013b4d99133e11","snaks":{"P4656":[{"snaktype":"value","property":"P4656","datavalue":{"value":"https://www.wikidata.org/w/index.php?title=Wikidata:Property_proposal/bilibili_ID&oldid=736360211","type":"string"},"datatype":"url"}]},"snaks-order":["P4656"]}]}],"P2429":[{"mainsnak":{"snaktype":"value","property":"P2429","datavalue":{"value":{"entity-type":"item","numeric-id":21873974,"id":"Q21873974"},"type":"wikibase-entityid"},"datatype":"wikibase-item"},"type":"statement","id":"P5733$5F02934B-BA90-44E5-806B-290B39BB882A","rank":"normal","references":[{"hash":"e58b97f86e2a3a4152287e2566013b4d99133e11","snaks":{"P4656":[{"snaktype":"value","property":"P4656","datavalue":{"value":"https://www.wikidata.org/w/index.php?title=Wikidata:Property_proposal/bilibili_ID&oldid=736360211","type":"string"},"datatype":"url"}]},"snaks-order":["P4656"]}]}],"P1659":[{"mainsnak":{"snaktype":"value","property":"P1659","datavalue":{"value":{"entity-type":"property","numeric-id":4110,"id":"P4110"},"type":"wikibase-entityid"},"datatype":"wikibase-property"},"type":"statement","id":"P5733$BC9D30E7-FC5A-4BD8-B42A-DB7B00CCBB80","rank":"normal","references":[{"hash":"e58b97f86e2a3a4152287e2566013b4d99133e11","snaks":{"P4656":[{"snaktype":"value","property":"P4656","datavalue":{"value":"https://www.wikidata.org/w/index.php?title=Wikidata:Property_proposal/bilibili_ID&oldid=736360211","type":"string"},"datatype":"url"}]},"snaks-order":["P4656"]}]}],"P1630":[{"mainsnak":{"snaktype":"value","property":"P1630","datavalue":{"value":"https://www.bilibili.com/bangumi/media/$1/","type":"string"},"datatype":"string"},"type":"statement","id":"P5733$87C9F43F-702D-4C2D-ACB6-777AFE42F14A","rank":"normal"}],"P2302":[{"mainsnak":{"snaktype":"value","property":"P2302","datavalue":{"value":{"entity-type":"item","numeric-id":19474404,"id":"Q19474404"},"type":"wikibase-entityid"},"datatype":"wikibase-item"},"type":"statement","id":"P5733$A078806B-1B8C-4C5B-8470-3302D53D3557","rank":"normal","references":[{"hash":"e58b97f86e2a3a4152287e2566013b4d99133e11","snaks":{"P4656":[{"snaktype":"value","property":"P4656","datavalue":{"value":"https://www.wikidata.org/w/index.php?title=Wikidata:Property_proposal/bilibili_ID&oldid=736360211","type":"string"},"datatype":"url"}]},"snaks-order":["P4656"]}]},{"mainsnak":{"snaktype":"value","property":"P2302","datavalue":{"value":{"entity-type":"item","numeric-id":21502410,"id":"Q21502410"},"type":"wikibase-entityid"},"datatype":"wikibase-item"},"type":"statement","id":"P5733$F1B6D2F2-FD37-4DC0-86F1-17CAB24D84F7","rank":"normal","references":[{"hash":"e58b97f86e2a3a4152287e2566013b4d99133e11","snaks":{"P4656":[{"snaktype":"value","property":"P4656","datavalue":{"value":"https://www.wikidata.org/w/index.php?title=Wikidata:Property_proposal/bilibili_ID&oldid=736360211","type":"string"},"datatype":"url"}]},"snaks-order":["P4656"]}]},{"mainsnak":{"snaktype":"value","property":"P2302","datavalue":{"value":{"entity-type":"item","numeric-id":21502404,"id":"Q21502404"},"type":"wikibase-entityid"},"datatype":"wikibase-item"},"type":"statement","qualifiers":{"P1793":[{"snaktype":"value","property":"P1793","hash":"8a5922159aba8bf5343f9f7f7139028fc1860bc9","datavalue":{"value":"md\\d{1,10}","type":"string"},"datatype":"string"}]},"qualifiers-order":["P1793"],"id":"P5733$37BB7B35-3334-4378-8DBA-D1CFAB36E29A","rank":"normal","references":[{"hash":"e58b97f86e2a3a4152287e2566013b4d99133e11","snaks":{"P4656":[{"snaktype":"value","property":"P4656","datavalue":{"value":"https://www.wikidata.org/w/index.php?title=Wikidata:Property_proposal/bilibili_ID&oldid=736360211","type":"string"},"datatype":"url"}]},"snaks-order":["P4656"]}]}],"P1793":[{"mainsnak":{"snaktype":"value","property":"P1793","datavalue":{"value":"md\\d+","type":"string"},"datatype":"string"},"type":"statement","id":"P5733$8CC766C0-A0B2-4701-B7B7-646BD6D2776D","rank":"normal","references":[{"hash":"e58b97f86e2a3a4152287e2566013b4d99133e11","snaks":{"P4656":[{"snaktype":"value","property":"P4656","datavalue":{"value":"https://www.wikidata.org/w/index.php?title=Wikidata:Property_proposal/bilibili_ID&oldid=736360211","type":"string"},"datatype":"url"}]},"snaks-order":["P4656"]}]}],"P31":[{"mainsnak":{"snaktype":"value","property":"P31","datavalue":{"value":{"entity-type":"item","numeric-id":19833377,"id":"Q19833377"},"type":"wikibase-entityid"},"datatype":"wikibase-item"},"type":"statement","id":"P5733$D1F52133-D8D1-454C-9B38-75E868C3A68B","rank":"normal"},{"mainsnak":{"snaktype":"value","property":"P31","datavalue":{"value":{"entity-type":"item","numeric-id":63871467,"id":"Q63871467"},"type":"wikibase-entityid"},"datatype":"wikibase-item"},"type":"statement","id":"P5733$9D92E196-F7AB-417A-8F1A-00C499C5B65B","rank":"normal"},{"mainsnak":{"snaktype":"value","property":"P31","datavalue":{"value":{"entity-type":"item","numeric-id":62589316,"id":"Q62589316"},"type":"wikibase-entityid"},"datatype":"wikibase-item"},"type":"statement","id":"P5733$c780aca6-4645-3358-90b9-36e1547c1cae","rank":"normal"}],"P1855":[{"mainsnak":{"snaktype":"value","property":"P1855","datavalue":{"value":{"entity-type":"item","numeric-id":281402,"id":"Q281402"},"type":"wikibase-entityid"},"datatype":"wikibase-item"},"type":"statement","qualifiers":{"P5733":[{"snaktype":"value","property":"P5733","hash":"7b3300214d93c972b0bd67f67019bef8bdc5f481","datavalue":{"value":"md425","type":"string"},"datatype":"external-id"}]},"qualifiers-order":["P5733"],"id":"P5733$A2514565-F94C-4A83-AFA1-3DBD509E839E","rank":"normal","references":[{"hash":"e58b97f86e2a3a4152287e2566013b4d99133e11","snaks":{"P4656":[{"snaktype":"value","property":"P4656","datavalue":{"value":"https://www.wikidata.org/w/index.php?title=Wikidata:Property_proposal/bilibili_ID&oldid=736360211","type":"string"},"datatype":"url"}]},"snaks-order":["P4656"]}]},{"mainsnak":{"snaktype":"value","property":"P1855","datavalue":{"value":{"entity-type":"item","numeric-id":30093113,"id":"Q30093113"},"type":"wikibase-entityid"},"datatype":"wikibase-item"},"type":"statement","qualifiers":{"P5733":[{"snaktype":"value","property":"P5733","hash":"4586f011e21612d25b3d1c16a7eae4a0f7b164e0","datavalue":{"value":"md102892","type":"string"},"datatype":"external-id"}]},"qualifiers-order":["P5733"],"id":"P5733$A208C143-75CA-4007-AFAC-513A32E3496B","rank":"normal","references":[{"hash":"e58b97f86e2a3a4152287e2566013b4d99133e11","snaks":{"P4656":[{"snaktype":"value","property":"P4656","datavalue":{"value":"https://www.wikidata.org/w/index.php?title=Wikidata:Property_proposal/bilibili_ID&oldid=736360211","type":"string"},"datatype":"url"}]},"snaks-order":["P4656"]}]},{"mainsnak":{"snaktype":"value","property":"P1855","datavalue":{"value":{"entity-type":"item","numeric-id":18705458,"id":"Q18705458"},"type":"wikibase-entityid"},"datatype":"wikibase-item"},"type":"statement","qualifiers":{"P5733":[{"snaktype":"value","property":"P5733","hash":"a01d80df9984da9d2a10983a47e347c6431d3771","datavalue":{"value":"md1691","type":"string"},"datatype":"external-id"}]},"qualifiers-order":["P5733"],"id":"P5733$BEA92883-7945-4666-8357-429A970FC6BF","rank":"normal","references":[{"hash":"e58b97f86e2a3a4152287e2566013b4d99133e11","snaks":{"P4656":[{"snaktype":"value","property":"P4656","datavalue":{"value":"https://www.wikidata.org/w/index.php?title=Wikidata:Property_proposal/bilibili_ID&oldid=736360211","type":"string"},"datatype":"url"}]},"snaks-order":["P4656"]}]},{"mainsnak":{"snaktype":"value","property":"P1855","datavalue":{"value":{"entity-type":"item","numeric-id":24554280,"id":"Q24554280"},"type":"wikibase-entityid"},"datatype":"wikibase-item"},"type":"statement","qualifiers":{"P5733":[{"snaktype":"value","property":"P5733","hash":"bd3ea70364047741c040a79162a2628a3686077a","datavalue":{"value":"md5064","type":"string"},"datatype":"external-id"}]},"qualifiers-order":["P5733"],"id":"P5733$48CD268A-042C-45CF-8551-61915F8CA15B","rank":"normal","references":[{"hash":"e58b97f86e2a3a4152287e2566013b4d99133e11","snaks":{"P4656":[{"snaktype":"value","property":"P4656","datavalue":{"value":"https://www.wikidata.org/w/index.php?title=Wikidata:Property_proposal/bilibili_ID&oldid=736360211","type":"string"},"datatype":"url"}]},"snaks-order":["P4656"]}]}]}}}}