{"entities":{"P6640":{"pageid":62385322,"ns":120,"title":"Property:P6640","lastrevid":905216547,"modified":"2019-04-06T17:58:01Z","type":"property","datatype":"external-id","id":"P6640","labels":{"en":{"language":"en","value":"JRC Names id"},"fr":{"language":"fr","value":"identifiant JRC Names"},"uk":{"language":"uk","value":"\u0456\u0434\u0435\u043d\u0442\u0438\u0444\u0456\u043a\u0430\u0442\u043e\u0440 JRC Names"},"ar":{"language":"ar","value":"\u0645\u0639\u0631\u0641 \u0623\u0633\u0645\u0627\u0621 \u0645\u0631\u0643\u0632 \u0627\u0644\u0628\u062d\u0648\u062b \u0627\u0644\u0645\u0634\u062a\u0631\u0643\u0629"},"nl":{"language":"nl","value":"JRC Names-identificatiecode"},"ca":{"language":"ca","value":"identificador JRC Names"}},"descriptions":{"en":{"language":"en","value":"ID in the JRC Names gazetteer, which provides spelling variants and EMM news about the entity (220k news items per day). Alias: JRCN"},"uk":{"language":"uk","value":"\u0456\u0434\u0435\u043d\u0442\u0438\u0444\u0456\u043a\u0430\u0442\u043e\u0440 \u0443 \u0434\u043e\u0432\u0456\u0434\u043d\u0438\u043a\u0443 JRC Names, \u044f\u043a\u0438\u0439 \u043d\u0430\u0434\u0430\u0454 \u0432\u0430\u0440\u0456\u0430\u043d\u0442\u0438 \u043e\u0440\u0444\u043e\u0433\u0440\u0430\u0444\u0456\u0457 \u0442\u0430 EMM-\u043d\u043e\u0432\u0438\u043d\u0438 \u043f\u0440\u043e \u043e\u0440\u0433\u0430\u043d\u0456\u0437\u0430\u0446\u0456\u0457 (220k \u043d\u043e\u0432\u0438\u043d \u043d\u0430 \u0434\u0435\u043d\u044c). \u041f\u0441\u0435\u0432\u0434\u043e\u043d\u0456\u043c: JRCN"}},"aliases":{"en":[{"language":"en","value":"JRCN"}],"ar":[{"language":"ar","value":"\u0623\u0633\u0645\u0627\u0621 \u0645\u0631\u0643\u0632 \u0627\u0644\u0628\u062d\u0648\u062b \u0627\u0644\u0645\u0634\u062a\u0631\u0643\u0629"}]},"claims":{"P31":[{"mainsnak":{"snaktype":"value","property":"P31","datavalue":{"value":{"entity-type":"item","numeric-id":19595382,"id":"Q19595382"},"type":"wikibase-entityid"},"datatype":"wikibase-item"},"type":"statement","id":"P6640$b8da50cc-486c-8559-2194-7d918ac6fd40","rank":"normal"},{"mainsnak":{"snaktype":"value","property":"P31","datavalue":{"value":{"entity-type":"item","numeric-id":19847637,"id":"Q19847637"},"type":"wikibase-entityid"},"datatype":"wikibase-item"},"type":"statement","id":"P6640$52e4b41d-4e15-9d00-0774-3f94935568b5","rank":"normal"}],"P3254":[{"mainsnak":{"snaktype":"value","property":"P3254","datavalue":{"value":"https://www.wikidata.org/wiki/Wikidata:Property_proposal/JRC_Names_id","type":"string"},"datatype":"url"},"type":"statement","id":"P6640$76582645-42c6-d745-46d2-b0c8392d505b","rank":"normal"}],"P1629":[{"mainsnak":{"snaktype":"value","property":"P1629","datavalue":{"value":{"entity-type":"item","numeric-id":62084229,"id":"Q62084229"},"type":"wikibase-entityid"},"datatype":"wikibase-item"},"type":"statement","id":"P6640$8d47f2cb-4b34-ec38-0782-28552de1ac98","rank":"normal"}],"P1630":[{"mainsnak":{"snaktype":"value","property":"P1630","datavalue":{"value":"http://emm.newsbrief.eu/NewsBrief/entityedition/en/$1.html","type":"string"},"datatype":"string"},"type":"statement","id":"P6640$b6ec37ff-4208-2424-7f78-bae8045a8945","rank":"normal"}],"P2429":[{"mainsnak":{"snaktype":"value","property":"P2429","datavalue":{"value":{"entity-type":"item","numeric-id":21873886,"id":"Q21873886"},"type":"wikibase-entityid"},"datatype":"wikibase-item"},"type":"statement","id":"P6640$c69c406e-4348-da75-0835-94dcbcbdd761","rank":"normal"}],"P1793":[{"mainsnak":{"snaktype":"value","property":"P1793","datavalue":{"value":"\\d+","type":"string"},"datatype":"string"},"type":"statement","id":"P6640$5e5de957-4602-dcf8-289a-4079b36f86b3","rank":"normal"}],"P1855":[{"mainsnak":{"snaktype":"value","property":"P1855","datavalue":{"value":{"entity-type":"item","numeric-id":146183,"id":"Q146183"},"type":"wikibase-entityid"},"datatype":"wikibase-item"},"type":"statement","qualifiers":{"P6640":[{"snaktype":"value","property":"P6640","hash":"b18752afc33eda45ebb527eda0c457141590eca1","datavalue":{"value":"100006","type":"string"},"datatype":"external-id"}]},"qualifiers-order":["P6640"],"id":"P6640$4d869ecc-48a8-40fa-10a2-329076a24eb9","rank":"normal"},{"mainsnak":{"snaktype":"value","property":"P1855","datavalue":{"value":{"entity-type":"item","numeric-id":80,"id":"Q80"},"type":"wikibase-entityid"},"datatype":"wikibase-item"},"type":"statement","qualifiers":{"P6640":[{"snaktype":"value","property":"P6640","hash":"281eb09a144334d0a47a42ec6a8b8225c9cbc342","datavalue":{"value":"61072","type":"string"},"datatype":"external-id"}]},"qualifiers-order":["P6640"],"id":"P6640$16c50ca2-4c9f-fea9-fdb2-12b91085658d","rank":"normal"},{"mainsnak":{"snaktype":"value","property":"P1855","datavalue":{"value":{"entity-type":"item","numeric-id":1851405,"id":"Q1851405"},"type":"wikibase-entityid"},"datatype":"wikibase-item"},"type":"statement","qualifiers":{"P6640":[{"snaktype":"value","property":"P6640","hash":"dcbacca9e8897186bd899b4b407da3a81171b15d","datavalue":{"value":"100029","type":"string"},"datatype":"external-id"}]},"qualifiers-order":["P6640"],"id":"P6640$a04f63f0-44c0-9a2a-8f32-9c12abd323d5","rank":"normal"},{"mainsnak":{"snaktype":"value","property":"P1855","datavalue":{"value":{"entity-type":"item","numeric-id":631612,"id":"Q631612"},"type":"wikibase-entityid"},"datatype":"wikibase-item"},"type":"statement","qualifiers":{"P6640":[{"snaktype":"value","property":"P6640","hash":"abc61543796dbf460811eb90e3fbfbb1732fffe7","datavalue":{"value":"1000097","type":"string"},"datatype":"external-id"}]},"qualifiers-order":["P6640"],"id":"P6640$c119f72e-4513-3961-fa7e-52db1442916c","rank":"normal"}],"P4876":[{"mainsnak":{"snaktype":"value","property":"P4876","datavalue":{"value":{"amount":"+662434","unit":"1"},"type":"quantity"},"datatype":"quantity"},"type":"statement","qualifiers":{"P585":[{"snaktype":"value","property":"P585","hash":"264543f28c3f7858284102cd66f3bb3be1269268","datavalue":{"value":{"time":"+2019-03-00T00:00:00Z","timezone":0,"before":0,"after":0,"precision":10,"calendarmodel":"http://www.wikidata.org/entity/Q1985727"},"type":"time"},"datatype":"time"}]},"qualifiers-order":["P585"],"id":"P6640$b02817fa-43e8-17a3-ca7b-be359f103de6","rank":"normal"}],"P2302":[{"mainsnak":{"snaktype":"value","property":"P2302","datavalue":{"value":{"entity-type":"item","numeric-id":21503250,"id":"Q21503250"},"type":"wikibase-entityid"},"datatype":"wikibase-item"},"type":"statement","qualifiers":{"P2309":[{"snaktype":"value","property":"P2309","hash":"8d7afee22e0fa6211dd8c95f247e1dd7b38daf70","datavalue":{"value":{"entity-type":"item","numeric-id":21503252,"id":"Q21503252"},"type":"wikibase-entityid"},"datatype":"wikibase-item"}],"P2308":[{"snaktype":"value","property":"P2308","hash":"6507af56cd83ccb72044b460a8b439e1746afa1a","datavalue":{"value":{"entity-type":"item","numeric-id":5,"id":"Q5"},"type":"wikibase-entityid"},"datatype":"wikibase-item"},{"snaktype":"value","property":"P2308","hash":"9c79957160f70512d894cf01e52c52b7b6f0aab0","datavalue":{"value":{"entity-type":"item","numeric-id":2029841,"id":"Q2029841"},"type":"wikibase-entityid"},"datatype":"wikibase-item"},{"snaktype":"value","property":"P2308","hash":"e7727b11cedec30bf3ef88dc2d8e03b06b250a95","datavalue":{"value":{"entity-type":"item","numeric-id":151885,"id":"Q151885"},"type":"wikibase-entityid"},"datatype":"wikibase-item"},{"snaktype":"value","property":"P2308","hash":"cdab508dc825b2c51c8729796a02900f76839dfe","datavalue":{"value":{"entity-type":"item","numeric-id":35120,"id":"Q35120"},"type":"wikibase-entityid"},"datatype":"wikibase-item"}]},"qualifiers-order":["P2309","P2308"],"id":"P6640$d69ac59f-4115-4e20-055c-c0a2183cc9d5","rank":"normal"},{"mainsnak":{"snaktype":"value","property":"P2302","datavalue":{"value":{"entity-type":"item","numeric-id":19474404,"id":"Q19474404"},"type":"wikibase-entityid"},"datatype":"wikibase-item"},"type":"statement","qualifiers":{"P2316":[{"snaktype":"value","property":"P2316","hash":"d50c571a43e6102d65b729ccc7049a0a2f867e34","datavalue":{"value":{"entity-type":"item","numeric-id":21502408,"id":"Q21502408"},"type":"wikibase-entityid"},"datatype":"wikibase-item"}]},"qualifiers-order":["P2316"],"id":"P6640$bb166a76-4c27-0415-35cd-8ad7881f5081","rank":"normal"},{"mainsnak":{"snaktype":"value","property":"P2302","datavalue":{"value":{"entity-type":"item","numeric-id":21502404,"id":"Q21502404"},"type":"wikibase-entityid"},"datatype":"wikibase-item"},"type":"statement","qualifiers":{"P1793":[{"snaktype":"value","property":"P1793","hash":"0f097f7a27ffc7b6db8518ca527f3cf417f6a473","datavalue":{"value":"\\d+","type":"string"},"datatype":"string"}]},"qualifiers-order":["P1793"],"id":"P6640$84a25e4b-4801-2799-a48f-75fcf847b269","rank":"normal"},{"mainsnak":{"snaktype":"value","property":"P2302","datavalue":{"value":{"entity-type":"item","numeric-id":53869507,"id":"Q53869507"},"type":"wikibase-entityid"},"datatype":"wikibase-item"},"type":"statement","qualifiers":{"P5314":[{"snaktype":"value","property":"P5314","hash":"a0202111cb525ed31611bf926974b74a2419b8ab","datavalue":{"value":{"entity-type":"item","numeric-id":54828448,"id":"Q54828448"},"type":"wikibase-entityid"},"datatype":"wikibase-item"},{"snaktype":"value","property":"P5314","hash":"9031ca220e943517fb8d671c4ad4f3f1a25b6a0b","datavalue":{"value":{"entity-type":"item","numeric-id":54828450,"id":"Q54828450"},"type":"wikibase-entityid"},"datatype":"wikibase-item"}]},"qualifiers-order":["P5314"],"id":"P6640$60f382b4-49bc-9983-a984-908c6f86407b","rank":"normal"}]}}}}